{"d2GfL8f/itTOQN1U+Dmc9w==":"a-24704a55d31179e4409d2a8b2c9ce5ac.gif","RNKQXSdQw3qWpt5iKI8Yxw==":"mbr-1920x1015.jpg","zjnDsutP6Y7TdBeeH+SVlA==":"unknown-656x898.png","cRvCevG8DJ7uYz4jegvRdQ==":"download-272x185.jpg","/gdR1OoN4/t1sN5oA12tGw==":"chadwick-boseman-red-carpet-gty-jc-200828_1598667557639_hpmain_16x9-1600-1600x900.jpg","SpWIy5rDGjhb9Fz7cypC6g==":"5f4a74af60bf1f00280795d1.webp","S3rb8iDZj4DD2D2xfXPpLA==":"ca-times.brightspotcdn-1486x899.jpg","lP4IfnpMiSgRmdLHyBXFNQ==":"200617_wn_bankert__hpmain_16x9-992-992x558.jpg","W5HzAZAZLkCH2lrRm7Q6gw==":"screenshot-800x481.png","h1AC8jTWiOEJSjxgj/v7jQ==":"5e2f23c0ab49fd12e34b8206.webp"}